TheSeedCore/Concurrent.py
TheSeedCore/Database.py
TheSeedCore/Logger.py
TheSeedCore/Network.py
TheSeedCore/Security.py
TheSeedCore/_Common.py
TheSeedCore/__init__.py
TheSeedCore-0.1.8.dist-info/LICENSE.txt
TheSeedCore-0.1.8.dist-info/METADATA
TheSeedCore-0.1.8.dist-info/WHEEL
TheSeedCore-0.1.8.dist-info/top_level.txt
TheSeedCore-0.1.8.dist-info/RECORD
