Metadata-Version: 2.1
Name: TheSeedCore
Version: 0.1.8
Summary: TheSeedCore is a comprehensive modular framework designed to meet the diverse needs of modern application development. Whether building high-performance, scalable applications or integrating complex systems, TheSeedCore provides a strong foundation covering a wide range of functions. With its modular, secure and flexible design, TheSeedCore can help developers create reliable and easy-to-maintain solutions.
Home-page: https://github.com/JFkirito/TheSeedCore
Author: 疾风Kirito
Author-email: 1453882193@qq.com
Classifier: Programming Language :: Python :: 3
Classifier: License :: OSI Approved :: MIT License
Requires-Python: >=3.11,<3.12
License-File: LICENSE.txt
